constants.py
ethct.py
ethct_contract.py
ethct_helper.py
ethct-19.11.1.dist-info/METADATA
ethct-19.11.1.dist-info/WHEEL
ethct-19.11.1.dist-info/entry_points.txt
ethct-19.11.1.dist-info/top_level.txt
ethct-19.11.1.dist-info/RECORD
