Metadata-Version: 2.1
Name: ethct
Version: 19.11.1
Summary: Ethereum contract tool(command line)
Home-page: https://github.com/ccyanxyz/ethct
Author: ccyanxyz
Author-email: ccyanxyz@gmail.com
License: UNKNOWN
Keywords: ethereum contract command-line-tool
Platform: UNKNOWN
Requires-Dist: web3 (>=4.2.1)
